odoo/addons/hr_operating_unit/README.rst
odoo/addons/hr_operating_unit/__init__.py
odoo/addons/hr_operating_unit/__manifest__.py
odoo/addons/hr_operating_unit/i18n/es.po
odoo/addons/hr_operating_unit/i18n/fr.po
odoo/addons/hr_operating_unit/i18n/hr_operating_unit.pot
odoo/addons/hr_operating_unit/i18n/it.po
odoo/addons/hr_operating_unit/models/__init__.py
odoo/addons/hr_operating_unit/models/hr_employee_base.py
odoo/addons/hr_operating_unit/models/hr_operating_unit.py
odoo/addons/hr_operating_unit/readme/CONTRIBUTORS.md
odoo/addons/hr_operating_unit/readme/DESCRIPTION.md
odoo/addons/hr_operating_unit/readme/USAGE.md
odoo/addons/hr_operating_unit/security/security.xml
odoo/addons/hr_operating_unit/static/description/icon.png
odoo/addons/hr_operating_unit/static/description/index.html
odoo/addons/hr_operating_unit/views/hr_employee.xml
odoo_addon_hr_operating_unit-17.0.1.0.0.3.dist-info/METADATA
odoo_addon_hr_operating_unit-17.0.1.0.0.3.dist-info/WHEEL
odoo_addon_hr_operating_unit-17.0.1.0.0.3.dist-info/top_level.txt
odoo_addon_hr_operating_unit-17.0.1.0.0.3.dist-info/RECORD
