Metadata-Version: 2.1
Name: odoo-addon-hr_operating_unit
Version: 17.0.1.0.0.3
Requires-Python: >=3.10
Requires-Dist: odoo-addon-operating_unit>=17.0dev,<17.1dev
Requires-Dist: odoo>=17.0a,<17.1dev
Summary: HR Operating Unit
Home-page: https://github.com/OCA/operating-unit
License: AGPL-3
Author: =?utf-8?q?Gonzalo_Gonz=C3=A1lez_Dom=C3=ADnguez=2C_Odoo_Community_Association_=28OCA=29?=
Author-email: support@odoo-community.org
Classifier: Programming Language :: Python
Classifier: Framework :: Odoo
Classifier: Framework :: Odoo :: 17.0
Classifier: License :: OSI Approved :: GNU Affero General Public License v3
